SEDFit/2MASS.H.dat
SEDFit/2MASS.J.dat
SEDFit/2MASS.Ks.dat
SEDFit/Cousins.B.dat
SEDFit/Cousins.I.dat
SEDFit/Cousins.R.dat
SEDFit/Cousins.U.dat
SEDFit/Cousins.V.dat
SEDFit/GAIA.GAIA3.G.dat
SEDFit/GAIA.GAIA3.Gbp.dat
SEDFit/GAIA.GAIA3.Grp.dat
SEDFit/GALEX.FUV.dat
SEDFit/GALEX.NUV.dat
SEDFit/Johnson.B.dat
SEDFit/Johnson.I.dat
SEDFit/Johnson.R.dat
SEDFit/Johnson.U.dat
SEDFit/Johnson.V.dat
SEDFit/PAN-STARRS.PS1.g.dat
SEDFit/PAN-STARRS.PS1.i.dat
SEDFit/PAN-STARRS.PS1.r.dat
SEDFit/PAN-STARRS.PS1.y.dat
SEDFit/PAN-STARRS.PS1.z.dat
SEDFit/SDSS.g.dat
SEDFit/SDSS.i.dat
SEDFit/SDSS.r.dat
SEDFit/SDSS.u.dat
SEDFit/SDSS.z.dat
SEDFit/WISE.W1.dat
SEDFit/WISE.W2.dat
SEDFit/WISE.W3.dat
SEDFit/__init__.py
SEDFit/sed.py
SEDFit/sed_btsettl.p
SEDFit/sed_coelho.p
SEDFit/sed_kurucz.p
SEDFit/sed_phoenix.p
SEDFit-0.4.dist-info/METADATA
SEDFit-0.4.dist-info/WHEEL
SEDFit-0.4.dist-info/top_level.txt
SEDFit-0.4.dist-info/RECORD
