Metadata-Version: 2.1
Name: SEDFit
Version: 0.4
Summary: Performs a model SED fitting to the stellar fluxes
Home-page: https://github.com/mkounkel/SEDFit
Author: Marina Kounkel
Author-email: marina.kounkel@vanderbilt.edu
Classifier: Programming Language :: Python :: 3
Classifier: License :: OSI Approved :: MIT License
Classifier: Operating System :: OS Independent
Requires-Python: >=3.6
Requires-Dist: astropy
Requires-Dist: numpy
Requires-Dist: scipy
Requires-Dist: dust-extinction
Requires-Dist: dustmaps
Requires-Dist: matplotlib
Requires-Dist: tqdm
